COPYING
MANIFEST.in
gpl.txt
setup.py
bin/cpd2ffen.py
bin/cpd2png.py
bin/cpd2popeye.py
bin/cpdb.py
bin/cpe.py
bin/demo.py
bin/import_authors.py
bin/import_check.py
bin/import_cities.py
bin/import_countries.py
bin/import_sources.py
bin/schwalbe_urdrucke.py
chessproblem/__init__.py
chessproblem/version.py
chessproblem/version_test.py
chessproblem.ui.egg-info/PKG-INFO
chessproblem.ui.egg-info/SOURCES.txt
chessproblem.ui.egg-info/dependency_links.txt
chessproblem.ui.egg-info/entry_points.txt
chessproblem.ui.egg-info/not-zip-safe
chessproblem.ui.egg-info/requires.txt
chessproblem.ui.egg-info/top_level.txt
chessproblem/board_drawing/__init__.py
chessproblem/config/__init__.py
chessproblem/config/config_template.py
chessproblem/config/config_test.py
chessproblem/image_files/__init__.py
chessproblem/image_files/images/32/0.png
chessproblem/image_files/images/32/0.xbm
chessproblem/image_files/images/32/1.png
chessproblem/image_files/images/32/1.xbm
chessproblem/image_files/images/32/10.png
chessproblem/image_files/images/32/10.xbm
chessproblem/image_files/images/32/100.png
chessproblem/image_files/images/32/100.xbm
chessproblem/image_files/images/32/101.png
chessproblem/image_files/images/32/101.xbm
chessproblem/image_files/images/32/102.png
chessproblem/image_files/images/32/102.xbm
chessproblem/image_files/images/32/103.png
chessproblem/image_files/images/32/103.xbm
chessproblem/image_files/images/32/104.png
chessproblem/image_files/images/32/104.xbm
chessproblem/image_files/images/32/105.png
chessproblem/image_files/images/32/105.xbm
chessproblem/image_files/images/32/106.png
chessproblem/image_files/images/32/106.xbm
chessproblem/image_files/images/32/107.png
chessproblem/image_files/images/32/107.xbm
chessproblem/image_files/images/32/108.png
chessproblem/image_files/images/32/108.xbm
chessproblem/image_files/images/32/109.png
chessproblem/image_files/images/32/109.xbm
chessproblem/image_files/images/32/11.png
chessproblem/image_files/images/32/11.xbm
chessproblem/image_files/images/32/110.png
chessproblem/image_files/images/32/110.xbm
chessproblem/image_files/images/32/111.png
chessproblem/image_files/images/32/111.xbm
chessproblem/image_files/images/32/112.png
chessproblem/image_files/images/32/112.xbm
