Metadata-Version: 1.1
Name: chessproblem.ui
Version: 1.2.0
Summary: The user interface to edit chessproblems for tex files using the chess-problem-diagrams latex style.
Home-page: http://sourceforge.net/projects/chessproblemed/
Author: Stefan Hoening
Author-email: Stefan.Hoening@web.de
License: GPL
Download-URL: http://pypi.python.org/packages/source/c/chessproblem.ui/chessproblem.ui-1.2.0.tar.gz
Keywords: chess problem user interface classes
Platform: UNKNOWN
Classifier: Programming Language :: Python :: 3.2
Classifier: Topic :: Games/Entertainment :: Board Games
Classifier: Environment :: X11 Applications :: GTK
Classifier: Intended Audience :: End Users/Desktop
Classifier: License :: OSI Approved :: GNU General Public License v3 or later (GPLv3+)
